mkdocs_semos_plugin/__init__.py
mkdocs_semos_plugin/plugin.py
mkdocs_semos_plugin-0.2.6.dist-info/LICENSE
mkdocs_semos_plugin-0.2.6.dist-info/METADATA
mkdocs_semos_plugin-0.2.6.dist-info/WHEEL
mkdocs_semos_plugin-0.2.6.dist-info/entry_points.txt
mkdocs_semos_plugin-0.2.6.dist-info/top_level.txt
mkdocs_semos_plugin-0.2.6.dist-info/RECORD
