Metadata-Version: 2.1
Name: mkdocs-semos-plugin
Version: 0.2.6
Summary: A MkDocs plugin
Home-page: UNKNOWN
Author: SeMoS
Author-email: semos2k@gmail.com
License: MIT
Keywords: mkdocs
Platform: UNKNOWN
Classifier: Development Status :: 4 - Beta
Classifier: Intended Audience :: Developers
Classifier: Intended Audience :: Information Technology
Classifier: License :: OSI Approved :: MIT License
Classifier: Programming Language :: Python
Classifier: Programming Language :: Python :: 3 :: Only
Classifier: Programming Language :: Python :: 3.4
Classifier: Programming Language :: Python :: 3.5
Classifier: Programming Language :: Python :: 3.6
Classifier: Programming Language :: Python :: 3.7
Requires-Python: >=2.7
Requires-Dist: mkdocs (==1.2.3)
Requires-Dist: mkdocs-material (==8.1.3)
Requires-Dist: mkdocs-material-extensions (==1.0.3)
